hst_tools/__init__.py
hst_tools/hgg_face.py
hst_tools/hs_logger.py
hst_tools-0.0.8.dist-info/LICENSE
hst_tools-0.0.8.dist-info/METADATA
hst_tools-0.0.8.dist-info/WHEEL
hst_tools-0.0.8.dist-info/top_level.txt
hst_tools-0.0.8.dist-info/RECORD
