Metadata-Version: 2.1
Name: hst_tools
Version: 0.0.8
Summary: That's all for work
Author-email: Dmytro <chernousan@gmail.com>
Requires-Python: >=3.10
License-File: LICENSE
